ymd/__init__.py
ymd/ymd.py
ymd-0.1.4.dist-info/LICENSE
ymd-0.1.4.dist-info/METADATA
ymd-0.1.4.dist-info/NOTICE
ymd-0.1.4.dist-info/WHEEL
ymd-0.1.4.dist-info/top_level.txt
ymd-0.1.4.dist-info/RECORD
