Metadata-Version: 2.1
Name: ymd
Version: 0.1.4
Summary: The ymd module supplies functions for manipulating dates
Home-page: https://github.com/andmeln/ymd/
Author: Andrey Melnikov
Author-email: andmeln@hotmail.com
License: Apache License, Version 2.0
Requires-Python: >=3.7
License-File: LICENSE
License-File: NOTICE
